basic_operations/__init__.py
basic_operations/operation.py
basic_operations-0.0.3.dist-info/METADATA
basic_operations-0.0.3.dist-info/WHEEL
basic_operations-0.0.3.dist-info/top_level.txt
basic_operations-0.0.3.dist-info/RECORD
