Metadata-Version: 2.1
Name: basic-operations
Version: 0.0.3
Summary: The package is used to basic mathematics operations
Home-page: https://github.com/roqueds/basic_operations_package
Author: Matheus Roque
Author-email: mroque@outlook.com.br
License: UNKNOWN
Platform: UNKNOWN
Requires-Python: >=3.8
